{
    "function_name": "fused_op_layout_cus_fe085104356880d7f9ef82195fd888f242cb1c38_2x3x32x32xfloat16_8x3x3x3xfloat16",
    "flat_args": [
        {
            "Formula": {
                "shape": [
                    2,
                    3,
                    32,
                    32
                ],
                "dtype": "float16",
                "coeff": 1,
                "offset": 0
            }
        },
        {
            "Formula": {
                "shape": [
                    8,
                    3,
                    3,
                    3
                ],
                "dtype": "float16",
                "coeff": 1,
                "offset": 0
            }
        }
    ],
    "seed": 1,
    "rtol": 0.005,
    "atol": 0.001,
    "equal_nan": false,
    "mode": "compare",
    "file_name": "test.mlir",
    "vmfb_name": "out.vmfb",
    "expected_output": [
        "expected_result_0.npy"
    ]
}
